Classfile /home/hero/workspace/JavaJava/Cookie/src/test/VolatileInt.class
  Last modified Aug 16, 2017; size 274 bytes
  MD5 checksum a28dc5bbaa843485e3ee015c2cdb9107
  Compiled from "VolatileInt.java"
public class VolatileInt
  minor version: 0
  major version: 52
  flags: ACC_PUBLIC, ACC_SUPER
Constant pool:
   #1 = Methodref          #3.#15         // java/lang/Object."<init>":()V
   #2 = Class              #16            // VolatileInt
   #3 = Class              #17            // java/lang/Object
   #4 = Utf8               t
   #5 = Utf8               I
   #6 = Utf8               <init>
   #7 = Utf8               ()V
   #8 = Utf8               Code
   #9 = Utf8               LineNumberTable
  #10 = Utf8               LocalVariableTable
  #11 = Utf8               this
  #12 = Utf8               LVolatileInt;
  #13 = Utf8               SourceFile
  #14 = Utf8               VolatileInt.java
  #15 = NameAndType        #6:#7          // "<init>":()V
  #16 = Utf8               VolatileInt
  #17 = Utf8               java/lang/Object
{
  int t;
    descriptor: I
    flags:

  public VolatileInt();
    descriptor: ()V
    flags: ACC_PUBLIC
    Code:
      stack=1, locals=1, args_size=1
         0: aload_0
         1: invokespecial #1                  // Method java/lang/Object."<init>":()V
         4: return
      LineNumberTable:
        line 4: 0
      LocalVariableTable:
        Start  Length  Slot  Name   Signature
            0       5     0  this   LVolatileInt;
}
SourceFile: "VolatileInt.java"
